README.md
setup.py
pyflwor/OrderedSet.py
pyflwor/__init__.py
pyflwor/examples.py
pyflwor/lexer.py
pyflwor/parser.py
pyflwor/pyflwor.py
pyflwor/repl.py
pyflwor/symbols.py
pyflwor/test_lexer.py
pyflwor/test_parser.py
pyflwor/test_pyflwor.py
pyflwor_ext.egg-info/PKG-INFO
pyflwor_ext.egg-info/SOURCES.txt
pyflwor_ext.egg-info/dependency_links.txt
pyflwor_ext.egg-info/requires.txt
pyflwor_ext.egg-info/top_level.txt