Metadata-Version: 1.0
Name: pyflwor-ext
Version: 1.2
Summary: A object query system for arbitrary python objects..
Home-page: https://www.github.com/timtadh/pyflwor
Author: Tim Henderson
Author-email: tim.tadh@gmail.com
License: BSD
Platform: UNKNOWN
